<xml xmlns="http://www.w3.org/1999/xhtml" collection="false">
  <block type="trade" id="73vWdDagX-YhN)CtN.3D" x="0" y="0">
    <statement name="SUBMARKET">
      <block type="variables_set" id="QSdm~%k+7~D0Z8pD44sy">
        <field name="VAR">prediction</field>
        <value name="VALUE">
          <block type="math_number" id="Bm/_14k}%TixIz)8q`}M">
            <field name="NUM">1</field>
          </block>
        </value>
        <next>
          <block type="market" id="~T:?7-`j{)c/H5e]d.H9">
            <field name="MARKET_LIST">volidx</field>
            <field name="SUBMARKET_LIST">random_index</field>
            <field name="SYMBOL_LIST">R_100</field>
            <field name="TRADETYPECAT_LIST">digits</field>
            <field name="TRADETYPE_LIST">matchesdiffers</field>
            <field name="TYPE_LIST">both</field>
            <field name="CANDLEINTERVAL_LIST">60</field>
            <field name="DURATIONTYPE_LIST">t</field>
            <field name="PAYOUTTYPE_LIST">stake</field>
            <field name="CURRENCY_LIST">USD</field>
            <field name="RESTARTONERROR">FALSE</field>
            <value name="DURATION">
              <block type="math_number" id="0p-bjjEuB1k(LNWLaiS]">
                <field name="NUM">5</field>
              </block>
            </value>
            <value name="AMOUNT">
              <block type="math_number" id="|tIC~6lHx]cKt9rf1jFk">
                <field name="NUM">1</field>
              </block>
            </value>
            <value name="PREDICTION">
              <block type="variables_get" id="JLnQm7|38I+x$n1;7R72">
                <field name="VAR">prediction</field>
              </block>
            </value>
          </block>
        </next>
      </block>
    </statement>
  </block>
  <block type="before_purchase" id="tOc)]Xd=cAm0aiy+-8(8" x="0" y="293">
    <statement name="BEFOREPURCHASE_STACK">
      <block type="controls_if" id="2[|fWu_91j^]NA=6k#04">
        <mutation else="1"></mutation>
        <value name="IF0">
          <block type="logic_compare" id="Lsv~]b`+%uz_GXWhS%z@">
            <field name="OP">EQ</field>
            <value name="A">
              <block type="variables_get" id="80]bwioct6z{0kpA8r@+">
                <field name="VAR">prediction</field>
              </block>
            </value>
            <value name="B">
              <block type="math_number" id="LeI_H[.PF;lb8f)5ytdu">
                <field name="NUM">1</field>
              </block>
            </value>
          </block>
        </value>
        <statement name="DO0">
          <block type="purchase" id="Q;`vp48|v7pG%t@W6`uQ">
            <field name="PURCHASE_LIST">DIGITMATCH</field>
          </block>
        </statement>
        <statement name="ELSE">
          <block type="purchase" id="NbQ`Fs/=3SjM^/ylcoh5">
            <field name="PURCHASE_LIST">DIGITDIFF</field>
          </block>
        </statement>
      </block>
    </statement>
  </block>
  <block type="after_purchase" id="Vt,CkLeK8E?%BmnB`~M)" x="0" y="471">
    <statement name="AFTERPURCHASE_STACK">
      <block type="variables_set" id="Ic5qrC:?c.=!f/VXc!@J">
        <field name="VAR">prediction</field>
        <value name="VALUE">
          <block type="math_number" id="$G*24Z.C1gH}G+SL53d+">
            <field name="NUM">2</field>
          </block>
        </value>
        <next>
          <block type="trade_again" id="SO*X=~i(5H%=zQ5%e+J$"></block>
        </next>
      </block>
    </statement>
  </block>
</xml>